st_package_reviewer/__init__.py
st_package_reviewer/__main__.py
st_package_reviewer/repo_tools.py
st_package_reviewer/runner.py
st_package_reviewer/check/__init__.py
st_package_reviewer/check/report.py
st_package_reviewer/check/file/__init__.py
st_package_reviewer/check/file/check_keymaps.py
st_package_reviewer/check/file/check_messages.py
st_package_reviewer/check/file/check_mousemaps.py
st_package_reviewer/check/file/check_no-sublime-package.py
st_package_reviewer/check/file/check_redundant_files.py
st_package_reviewer/check/file/check_resource_file_validity.py
st_package_reviewer/check/file/check_resource_files.py
st_package_reviewer/check/file/ast/__init__.py
st_package_reviewer/check/file/ast/check_command_names.py
st_package_reviewer/check/file/ast/check_initialized_api.py
st_package_reviewer/check/file/ast/check_os_system_calls.py
st_package_reviewer/check/file/ast/check_platform_usage.py
st_package_reviewer/check/repo/__init__.py
st_package_reviewer/check/repo/check_readme.py
st_package_reviewer/check/repo/check_tags.py
st_package_reviewer/data/Default (Linux).sublime-keymap
st_package_reviewer/data/Default (OSX).sublime-keymap
st_package_reviewer/data/Default (Windows).sublime-keymap
st_package_reviewer/data/VERSION
st_package_reviewer/lib/__init__.py
st_package_reviewer/lib/jsonc.py
st_package_reviewer/lib/semver.py
st_package_reviewer-0.3.0.dist-info/DESCRIPTION.rst
st_package_reviewer-0.3.0.dist-info/METADATA
st_package_reviewer-0.3.0.dist-info/RECORD
st_package_reviewer-0.3.0.dist-info/WHEEL
st_package_reviewer-0.3.0.dist-info/entry_points.txt
st_package_reviewer-0.3.0.dist-info/metadata.json
st_package_reviewer-0.3.0.dist-info/top_level.txt
