Metadata-Version: 2.0
Name: st-package-reviewer
Version: 0.3.0
Summary: Review Sublime Text packages
Home-page: https://github.com/packagecontrol/st_package_reviewer
Author: FichteFoll
Author-email: fichtefoll2@googlemail.com
License: MIT
Keywords: sublime text,review,reviewer,package,package control
Platform: UNKNOWN
Classifier: Development Status :: 4 - Beta
Classifier: Intended Audience :: Developers
Classifier: Topic :: Software Development :: Quality Assurance
Classifier: License :: OSI Approved :: MIT License
Classifier: Operating System :: OS Independent
Classifier: Environment :: Console
Classifier: Programming Language :: Python :: 3
Classifier: Programming Language :: Python :: 3.4
Classifier: Programming Language :: Python :: 3.5
Classifier: Programming Language :: Python :: 3.6
Requires-Dist: github3.py (>=1.0.0a4)
Requires-Dist: pyperclip
